infrascloudy/__init__.py
infrascloudy/dump.py
infrascloudy/main.py
infrascloudy/metadata.py
infrascloudy/render.py
infrascloudy/templates.py
infrascloudy/types.py
infrascloudy/values.py
infrascloudy/utils/__init__.py
infrascloudy/utils/dict.py
infrascloudy/utils/yaml.py
infrascloudy/utils/tests/__init__.py
infrascloudy/utils/tests/test_dict.py
infrascloudy-0.1.1.dist-info/LICENSE
infrascloudy-0.1.1.dist-info/METADATA
infrascloudy-0.1.1.dist-info/WHEEL
infrascloudy-0.1.1.dist-info/entry_points.txt
infrascloudy-0.1.1.dist-info/top_level.txt
infrascloudy-0.1.1.dist-info/RECORD
