Metadata-Version: 2.1
Name: infrascloudy
Version: 0.1.1
Summary: It does cloudy things
Home-page: http://taiosolve.xyz/
Author: Allan Swanepoel
Author-email: support@taiosolve.xyz
Maintainer: Allan Swanepoel
Maintainer-email: support@taiosolve.xyz
License: UNKNOWN
Platform: UNKNOWN
Classifier: Development Status :: 1 - Planning
Classifier: Environment :: Console
Classifier: Intended Audience :: Developers
Classifier: License :: OSI Approved :: MIT License
Classifier: Natural Language :: English
Classifier: Operating System :: OS Independent
Classifier: Programming Language :: Python :: 2.6
Classifier: Programming Language :: Python :: 2.7
Classifier: Programming Language :: Python :: 3.3
Classifier: Programming Language :: Python :: Implementation :: PyPy
Classifier: Topic :: Documentation
Classifier: Topic :: Software Development :: Libraries :: Python Modules
Classifier: Topic :: System :: Installation/Setup
Classifier: Topic :: System :: Software Distribution
